cronutils/__init__.py
cronutils/error_handler.py
cronutils/process_handler.py
cronutils/task_runner.py
cronutils-0.5.0.dist-info/licenses/LICENSE
cronutils-0.5.0.dist-info/METADATA
cronutils-0.5.0.dist-info/WHEEL
cronutils-0.5.0.dist-info/top_level.txt
cronutils-0.5.0.dist-info/RECORD
