Metadata-Version: 2.4
Name: cronutils
Version: 0.5.0
Summary: Tool designed to simplify the configuration and dispatching of tasks via cron
Author-email: "Zagaran, Inc." <info@zagaran.com>
License-Expression: MIT
Project-URL: Homepage, https://github.com/zagaran/cronutils
Keywords: cron,crontab,task,error,handling
Classifier: Development Status :: 4 - Beta
Classifier: Operating System :: MacOS :: MacOS X
Classifier: Operating System :: Microsoft :: Windows
Classifier: Operating System :: POSIX
Classifier: Programming Language :: Python
Classifier: Topic :: Utilities
Requires-Python: >=3.6
License-File: LICENSE
Requires-Dist: sentry-sdk>=1.0.0
Dynamic: license-file
